xprcess_img/__init__.py
xprcess_img/processing/__init__.py
xprcess_img/processing/combination.py
xprcess_img/processing/transformation.py
xprcess_img/utils/__init__.py
xprcess_img/utils/io.py
xprcess_img/utils/plot.py
xprcess_img-0.0.1.dist-info/METADATA
xprcess_img-0.0.1.dist-info/WHEEL
xprcess_img-0.0.1.dist-info/top_level.txt
xprcess_img-0.0.1.dist-info/RECORD
