Metadata-Version: 2.4
Name: xprcess_img
Version: 0.0.1
Home-page: https://github.com/engcarlo/image-processing-package
Author: yukio
Author-email: o.manifesto.da.riqueza@gmail.com
Requires-Python: >=3.8
Dynamic: author
Dynamic: author-email
Dynamic: description
Dynamic: description-content-type
Dynamic: home-page
Dynamic: requires-python
